{
  "status": [
    {"key": "Active", "count": 741251},
    {"key": "Inactive", "count": 331024},
    {"key": "Archived", "count": 245681},
    {"key": "Canceled", "count": 256476}
  ],
  "type": [
    {"key": "presol", "count": 741251},
    {"key": "type 3", "count": 331024},
    {"key": "grant", "count": 245681},
    {"key": "contract", "count": 256476}
  ],
  "consumer": [
    {"key": "Department of Defense", "count": 741251},
    {"key": "General Services Administration", "count": 331024},
    {"key": "Department of Commerce", "count": 245681},
    {"key": "Department of Homeland Security", "count": 256476},
    {"key": "Federal Acquisition Services", "count": 256346},
    {"key": "Department of Defense", "count": 741251},
    {"key": "General Services Administration", "count": 331024},
    {"key": "Department of Commerce", "count": 245681},
    {"key": "Department of Homeland Security", "count": 256476},
    {"key": "Federal Acquisition Services", "count": 556346},
    {"key": "Department of Defense", "count": 741251},
    {"key": "General Services Administration", "count": 331024},
    {"key": "Department of Commerce", "count": 245681},
    {"key": "Department of Homeland Security", "count": 256476},
    {"key": "Federal Acquisition Services", "count": 256346},
    {"key": "Department of Defense", "count": 741251},
    {"key": "General Services Administration", "count": 631024},
    {"key": "Department of Commerce", "count": 745681},
    {"key": "Department of Homeland Security", "count": 456476},
    {"key": "Federal Acquisition Services", "count": 256116}
  ],
  "map": [
    { "key": "AL", "count": 234 },
    { "key": "AK", "count": 489 },
    { "key": "AZ", "count": 172 },
    { "key": "AR", "count": 742 },
    { "key": "CA", "count": 2340 },
    { "key": "CO", "count": 864 },
    { "key": "CT", "count": 365 },
    { "key": "DE", "count": 500 },
    { "key": "DC", "count": 100 },
    { "key": "FL", "count": 475 },
    { "key": "GA", "count": 234 },
    { "key": "HI", "count": 489 },
    { "key": "ID", "count": 234 },
    { "key": "IL", "count": 489 },
    { "key": "IN", "count": 234 },
    { "key": "IA", "count": 489 },
    { "key": "KS", "count": 234 },
    { "key": "KY", "count": 489 },
    { "key": "LA", "count": 234 },
    { "key": "ME", "count": 489 },
    { "key": "MD", "count": 234 },
    { "key": "MA", "count": 489 },
    { "key": "MI", "count": 234 },
    { "key": "MN", "count": 489 },
    { "key": "MS", "count": 234 },
    { "key": "MO", "count": 489 },
    { "key": "MT", "count": 234 },
    { "key": "NE", "count": 489 },
    { "key": "NV", "count": 234 },
    { "key": "NH", "count": 489 },
    { "key": "NJ", "count": 234 },
    { "key": "NM", "count": 489 },
    { "key": "NY", "count": 234 },
    { "key": "NC", "count": 489 },
    { "key": "ND", "count": 234 },
    { "key": "OH", "count": 489 },
    { "key": "OK", "count": 234 },
    { "key": "OR", "count": 489 },
    { "key": "PA", "count": 234 },
    { "key": "RI", "count": 489 },
    { "key": "SC", "count": 234 },
    { "key": "SD", "count": 489 },
    { "key": "TN", "count": 234 },
    { "key": "TX", "count": 489 },
    { "key": "UT", "count": 234 },
    { "key": "VT", "count": 489 },
    { "key": "VA", "count": 234 },
    { "key": "WA", "count": 489 },
    { "key": "WV", "count": 234 },
    { "key": "WI", "count": 489 },
    { "key": "WY", "count": 234 }
  ]
}